rabbitmq_consume/__init__.py
rabbitmq_consume/__main__.py
rabbitmq_consume/connection_utils.py
rabbitmq_consume/consumer.py
rabbitmq_consume/consumption.py
rabbitmq_consume/null_consumption.py
rabbitmq_consume/print_consumption.py
rabbitmq_consume/pusher.py
rabbitmq_consume/rmq_consume.py
rabbitmq_consume/rmq_push.py
rabbitmq_consume/utils.py
rabbitmq_consume/worker.py
rabbitmq_consume-1.0.0.dist-info/LICENSE.txt
rabbitmq_consume-1.0.0.dist-info/METADATA
rabbitmq_consume-1.0.0.dist-info/WHEEL
rabbitmq_consume-1.0.0.dist-info/entry_points.txt
rabbitmq_consume-1.0.0.dist-info/top_level.txt
rabbitmq_consume-1.0.0.dist-info/RECORD
