Metadata-Version: 2.1
Name: rabbitmq-consume
Version: 1.0.0
Summary: Consumes XML messages from a RabbitMQ queue using a user defined class.
Author-email: Simon Patton <sjpatton@lbl.gov>
License: BSD-3-Clause-LBNL
Keywords: rabbitmq,rabbitmq_consume
Classifier: Development Status :: 1 - Planning 
Classifier: Intended Audience :: Developers
Classifier: Topic :: Scientific/Engineering
Classifier: Programming Language :: Python :: 3.8
Requires-Python: <4,>=3.10
License-File: LICENSE.txt
Requires-Dist: pika (>=1.3)
